annobel/__init__.py
annobel/_core.py
annobel/main.py
annobel-0.0.3.dist-info/licenses/LICENSE
annobel-0.0.3.dist-info/METADATA
annobel-0.0.3.dist-info/WHEEL
annobel-0.0.3.dist-info/entry_points.txt
annobel-0.0.3.dist-info/top_level.txt
annobel-0.0.3.dist-info/RECORD
