Metadata-Version: 2.4
Name: annobel
Version: 0.0.3
Summary: Automatic + manual YOLO bounding box annotation tool (GUI + console)
Home-page: https://github.com/SayaliDongre/annobel
Author: Sayali Dongre
Author-email: Sayali Dongre <sayalidongre25@gmail.com>
License:                     GNU AFFERO GENERAL PUBLIC LICENSE
Project-URL: Homepage, https://github.com/SayaliDongre/annobel
Project-URL: Source, https://github.com/SayaliDongre/annobel
Project-URL: Issues, https://github.com/SayaliDongre/annobel/issues
Project-URL: Ultralytics, https://github.com/ultralytics/ultralytics
Classifier: Development Status :: 3 - Alpha
Classifier: Intended Audience :: Developers
Classifier: Intended Audience :: Science/Research
Classifier: Topic :: Scientific/Engineering :: Artificial Intelligence
Classifier: License :: OSI Approved :: GNU Affero General Public License v3 or later (AGPLv3+)
Classifier: Programming Language :: Python :: 3
Classifier: Programming Language :: Python :: 3.8
Classifier: Programming Language :: Python :: 3.9
Classifier: Programming Language :: Python :: 3.10
Classifier: Programming Language :: Python :: 3.11
Classifier: Programming Language :: Python :: 3.12
Classifier: Environment :: Console
Classifier: Environment :: X11 Applications :: GTK
Classifier: Operating System :: OS Independent
Requires-Python: >=3.8
License-File: LICENSE
Requires-Dist: ultralytics>=8.0.0
Requires-Dist: pillow>=9.0.0
Provides-Extra: dev
Requires-Dist: black; extra == "dev"
Requires-Dist: flake8; extra == "dev"
Requires-Dist: mypy; extra == "dev"
Requires-Dist: pytest; extra == "dev"
Dynamic: author
Dynamic: home-page
Dynamic: license-file
Dynamic: requires-python
